mihomo/__init__.py
mihomo/api.py
mihomo/model.py
mihomo-3.6.0.dist-info/LICENSE
mihomo-3.6.0.dist-info/METADATA
mihomo-3.6.0.dist-info/WHEEL
mihomo-3.6.0.dist-info/RECORD
